[
    {
        "id": 1,
        "category": "차량 문의",
        "contentSummary": "안녕하세요 넌 바보야 나는짱임",
        "status": "답변 완료",
        "userName": "이다현",
        "date": "2024-02-02"
    },
    {
        "id": 2,
        "category": "차량 문의",
        "contentSummary": "안녕하세요 넌 바보야 나는짱임",
        "status": "답변 완료",
        "userName": "이다현",
        "date": "2024-02-02"
    },
    {
        "id": 3,
        "category": "차량 문의",
        "contentSummary": "안녕하세요 넌 바보야 나는짱임",
        "status": "답변 완료",
        "userName": "이다현",
        "date": "2024-02-02"
    },
    {
        "id": 4,
        "category": "차량 문의",
        "contentSummary": "안녕하세요 넌 바보야 나는짱임",
        "status": "답변 완료",
        "userName": "이다현",
        "date": "2024-02-02"
    },
    {
        "id": 5,
        "category": "차량 문의",
        "contentSummary": "안녕하세요 넌 바보야 나는짱임",
        "status": "답변 완료",
        "userName": "이다현",
        "date": "2024-02-02"
    },
    {
        "id": 6,
        "category": "차량 문의",
        "contentSummary": "안녕하세요 넌 바보야 나는짱임",
        "status": "답변 완료",
        "userName": "이다현",
        "date": "2024-02-02"
    },
    {
        "id": 7,
        "category": "차량 문의",
        "contentSummary": "안녕하세요 넌 바보야 나는짱임",
        "status": "답변 완료",
        "userName": "이다현",
        "date": "2024-02-02"
    },
    {
        "id": 8,
        "category": "차량 문의",
        "contentSummary": "안녕하세요 넌 바보야 나는짱임",
        "status": "답변 완료",
        "userName": "이다현",
        "date": "2024-02-02"
    }
]